{
  "metadata": {
    "task_id": "99a1516a-d340-4746-bb00-bef1850da253",
    "extraction_date": "2025-07-14T09:34:28.129007",
    "session_id": "20250714_093420",
    "pages_scanned": 10,
    "pages_with_content": 6,
    "total_highlights": 4,
    "extraction_method": "individual_highlights",
    "version": "3.0"
  },
  "statistics": {
    "confidence": {
      "average": 93.2,
      "min": 91.80555555555556,
      "max": 94.0,
      "distribution": {
        "high": 4,
        "medium": 0,
        "low": 0
      }
    },
    "text": {
      "total_words": 185,
      "average_words_per_highlight": 46.2,
      "min_words": 3,
      "max_words": 103
    },
    "pages": {
      "total_pages": 2,
      "highlights_per_page": 2.0
    }
  },
  "highlights": [
    {
      "id": "2b18dee1-2aad-47ff-97c4-1b5ee54009ec",
      "unique_id": "20250714_093420_page007_highlight01",
      "book_id": "4757ac22-a0a7-4fee-a84f-91c003b8b355",
      "page_number": 7,
      "highlight_number": 1,
      "text": "par une assistante maternelle des Ardennes acca- blée par la fermeture du collège de sa commune, un François Hollande plein de compassion botte en touche, puis chante les louanges de son « grand plan numérique » pour l’école, avec « cours de codage » et équipement des établissements en PC et tablettes. Soit le projet correspondant au volet «e-éducation » de sa brochette de « 34 plans de la nouvelle France industrielle? Comme s’il allait de soi que le numérique représente aujourd’hui LA solution à la désertification des campagnes, à la cure d’austérité des communes ou à l’inadapta- tion de nos institutions scolaires.",
      "confidence": 94.0,
      "confidence_level": "HIGH",
      "extracted_at": "2025-07-14T09:34:20.866702",
      "session_id": "20250714_093420",
      "position": {
        "x": 1284,
        "y": 138,
        "width": 540,
        "height": 502
      },
      "metrics": {
        "word_count": 103,
        "character_count": 623,
        "preview": "par une assistante maternelle des Ardennes acca- blée par la fermeture du collège de sa commune, ..."
      },
      "position_info": {
        "x": 1284,
        "y": 138,
        "width": 540,
        "height": 502,
        "area": 271080,
        "aspect_ratio": 1.0756972111553784,
        "center_x": 1554,
        "center_y": 389
      }
    },
    {
      "id": "5bae7493-d01e-48f5-b434-94d3835d4b87",
      "unique_id": "20250714_093428_page010_highlight01",
      "book_id": "4757ac22-a0a7-4fee-a84f-91c003b8b355",
      "page_number": 10,
      "highlight_number": 1,
      "text": "La Société auto-",
      "confidence": 93.3,
      "confidence_level": "HIGH",
      "extracted_at": "2025-07-14T09:34:28.122753",
      "session_id": "20250714_093428",
      "position": {
        "x": 1598,
        "y": 176,
        "width": 176,
        "height": 46
      },
      "metrics": {
        "word_count": 3,
        "character_count": 16,
        "preview": "La Société auto-"
      },
      "position_info": {
        "x": 1598,
        "y": 176,
        "width": 176,
        "height": 46,
        "area": 8096,
        "aspect_ratio": 3.8260869565217392,
        "center_x": 1686,
        "center_y": 199
      }
    },
    {
      "id": "4305b58e-3771-47c6-9214-d25c0531a442",
      "unique_id": "20250714_093428_page010_highlight03",
      "book_id": "4757ac22-a0a7-4fee-a84f-91c003b8b355",
      "page_number": 10,
      "highlight_number": 3,
      "text": "Pour Bernard Stiegler, au cours des vingt pro- chaines années, la vague de l'automatisation va déferler et peu à peu détruire l'emploi. Comment réagir à ce changement radical ? Selon lui, plutôt que de s'opposer frontalement à la lente et inexo- rable destruction du salariat par nos multiples au- tomates de l’ére numérique, l'enjeu réside d’abord dans la nécessité de combattre l’« automatisation des esprits ». Que veut-il dire par là ?",
      "confidence": 91.8,
      "confidence_level": "HIGH",
      "extracted_at": "2025-07-14T09:34:28.123076",
      "session_id": "20250714_093428",
      "position": {
        "x": 1284,
        "y": 451,
        "width": 539,
        "height": 350
      },
      "metrics": {
        "word_count": 72,
        "character_count": 439,
        "preview": "Pour Bernard Stiegler, au cours des vingt pro- chaines années, la vague de l'automatisation va dé..."
      },
      "position_info": {
        "x": 1284,
        "y": 451,
        "width": 539,
        "height": 350,
        "area": 188650,
        "aspect_ratio": 1.54,
        "center_x": 1553,
        "center_y": 626
      }
    },
    {
      "id": "30ee7ba1-355e-4c06-a163-1ee32ebc1d68",
      "unique_id": "20250714_093428_page010_highlight04",
      "book_id": "4757ac22-a0a7-4fee-a84f-91c003b8b355",
      "page_number": 10,
      "highlight_number": 4,
      "text": "Elle part d’un constat : les nou-",
      "confidence": 93.9,
      "confidence_level": "HIGH",
      "extracted_at": "2025-07-14T09:34:28.123348",
      "session_id": "20250714_093428",
      "position": {
        "x": 1483,
        "y": 916,
        "width": 338,
        "height": 46
      },
      "metrics": {
        "word_count": 7,
        "character_count": 33,
        "preview": "Elle part d’un constat : les nou-"
      },
      "position_info": {
        "x": 1483,
        "y": 916,
        "width": 338,
        "height": 46,
        "area": 15548,
        "aspect_ratio": 7.3478260869565215,
        "center_x": 1652,
        "center_y": 939
      }
    }
  ],
  "pages": {
    "7": {
      "page_number": 7,
      "highlight_count": 1,
      "highlights": [
        {
          "highlight_number": 1,
          "text": "par une assistante maternelle des Ardennes acca- blée par la fermeture du collège de sa commune, un François Hollande plein de compassion botte en touche, puis chante les louanges de son « grand plan numérique » pour l’école, avec « cours de codage » et équipement des établissements en PC et tablettes. Soit le projet correspondant au volet «e-éducation » de sa brochette de « 34 plans de la nouvelle France industrielle? Comme s’il allait de soi que le numérique représente aujourd’hui LA solution à la désertification des campagnes, à la cure d’austérité des communes ou à l’inadapta- tion de nos institutions scolaires.",
          "confidence": 94.0,
          "word_count": 103,
          "character_count": 623,
          "preview": "par une assistante maternelle des Ardennes acca- b..."
        }
      ]
    },
    "10": {
      "page_number": 10,
      "highlight_count": 3,
      "highlights": [
        {
          "highlight_number": 1,
          "text": "La Société auto-",
          "confidence": 93.33333333333333,
          "word_count": 3,
          "character_count": 16,
          "preview": "La Société auto-"
        },
        {
          "highlight_number": 3,
          "text": "Pour Bernard Stiegler, au cours des vingt pro- chaines années, la vague de l'automatisation va déferler et peu à peu détruire l'emploi. Comment réagir à ce changement radical ? Selon lui, plutôt que de s'opposer frontalement à la lente et inexo- rable destruction du salariat par nos multiples au- tomates de l’ére numérique, l'enjeu réside d’abord dans la nécessité de combattre l’« automatisation des esprits ». Que veut-il dire par là ?",
          "confidence": 91.80555555555556,
          "word_count": 72,
          "character_count": 439,
          "preview": "Pour Bernard Stiegler, au cours des vingt pro- cha..."
        },
        {
          "highlight_number": 4,
          "text": "Elle part d’un constat : les nou-",
          "confidence": 93.85714285714286,
          "word_count": 7,
          "character_count": 33,
          "preview": "Elle part d’un constat : les nou-"
        }
      ]
    }
  }
}